{
  "year": 2023,
  "exam": "GATE ST",
  "question_id": "Q46",
  "question_seq": 39,
  "question_type": "MCQ",
  "marks": null,
  "difficulty": null,
  "concept_id": "PROB_001",
  "question_text": "Let X be a random variable with cumulative distribution function $ F ( x ) = { \\left\\{ \\begin{array} { l l } { 0 } & { { \\mathrm { i f ~ } } x < - 1 } \\\\ { { \\frac { 1 } { 4 } } ( x + 1 ) } & { { \\mathrm { i f ~ } } - 1 \\leq x < 0 } \\\\ { { \\frac { 1 } { 4 } } ( x + 3 ) } & { { \\mathrm { i f ~ } } 0 \\leq x < 1 } \\\\ { 1 } & { { \\mathrm { i f ~ } } x \\geq 1 } \\end{array} \\right. } $ Which one of the following statements is true?",
  "options": {
    "A": "$\\begin{array} { r } { \\operatorname* { l i m } _ { n \\to \\infty } P \\left( - \\frac { 1 } { 2 } + \\frac { 1 } { n } < X < - 1 - \\frac { 1 } { n } \\right) = \\frac { 5 } { 8 } } \\end{array}$",
    "B": "$\\begin{array} { r } { \\operatorname* { l i m } _ { n \\to \\infty } P \\left( - \\frac { 1 } { 2 } - \\frac { 1 } { n } < X < 1 - \\frac { 1 } { n } \\right) = \\frac { 5 } { 8 } } \\end{array}$",
    "C": "$\\begin{array} { r } { \\operatorname* { l i m } _ { n \\to \\infty } P \\left( X = - \\frac { 1 } { n } \\right) = \\frac { 1 } { 2 } } \\end{array}$",
    "D": "$\\begin{array} { r } { P ( X = 0 ) = \\frac { 1 } { 3 } } \\end{array}$"
  },
  "answer": "B",
  "solution": "1) Understanding the cumulative distribution function (CDF):\n\nThe given CDF describes a piecewise function for X. We will use this function to calculate the probabilities for different intervals.\n\n2) Analysis of the options:\n\n(A) Incorrect: This option asks for the probability $\\begin{array} { r } { P \\left( - \\frac { 1 } { 2 } + \\frac { 1 } { n } < X < - 1 - \\frac { 1 } { n } \\right) } \\end{array}$ . As $n \\to \\infty$ the interval becomes a small neighborhood around −1, but the probability is not equal to $\\frac { 5 } { 8 }$ .\n\n(B) Correct: This option asks for the probability $\\begin{array} { r } { P \\left( - \\frac { 1 } { 2 } - \\frac { 1 } { n } < X < 1 - \\frac { 1 } { n } \\right) } \\end{array}$ . As $n \\to \\infty$ , the interval approaches the entire range $[ - \\frac { 1 } { 2 } , 1 ]$ , for which the CDF gives a probability of $\\frac { 5 } { 8 }$\n\n(C) Incorrect: This option concerns $\\textstyle P ( X = - { \\frac { 1 } { n } } )$ , but $P ( X = x )$ for a continuous random variable is always zero.\n\n(D) Incorrect: The probability $P ( X = 0 )$ is not $\\frac { 1 } { 3 }$ because the CDF at a single point does not give a nonzero value for continuous random variables.\n\nThe correct answer is (B).\nQuick Tip\n\n\\- For continuous distributions, the probability at a single point is always zero.\n\n\\- The CDF can be used to calculate probabilities over intervals."
}