{
  "year": 2021,
  "exam": "GATE ST",
  "question_id": "Q18",
  "question_seq": 33,
  "question_type": "NAT",
  "marks": null,
  "difficulty": null,
  "concept_id": "PROB_001",
  "question_text": "For α > 0, let {X(α) n }n≥1 be a sequence of independent random variables such that P(X(α) = 1) = n2α = 1−P(X(α) Let S = {α > 0 : X(α)",
  "options": {
    "C": "onverges to 0 almost surely as n →∞}. Then the infimum of S equals (round off to 2 decimal places)."
  },
  "answer": null,
  "solution": "Given that P(X(α)\n= 1) =\nn2α, the condition for convergence to 0 almost surely is determined\nby the behavior of the series. Using the criteria for almost sure convergence of independent\nrandom variables, we conclude that:\ninf S = 0.50.\nThus, the value is 0.50.\nQuick Tip\nFor sequences of independent random variables, the infimum for convergence is deter-\nmined by examining the sum of the probabilities and using convergence criteria."
}